CHANGES.txt
CONTRIBUTORS.txt
MANIFEST.in
README.txt
setup.cfg
setup.py
docs/HISTORY.txt
docs/INSTALL.txt
docs/LICENSE.GPL
docs/LICENSE.txt
wildcard/__init__.py
wildcard.pfg.stripe.egg-info/PKG-INFO
wildcard.pfg.stripe.egg-info/SOURCES.txt
wildcard.pfg.stripe.egg-info/dependency_links.txt
wildcard.pfg.stripe.egg-info/entry_points.txt
wildcard.pfg.stripe.egg-info/namespace_packages.txt
wildcard.pfg.stripe.egg-info/not-zip-safe
wildcard.pfg.stripe.egg-info/paster_plugins.txt
wildcard.pfg.stripe.egg-info/requires.txt
wildcard.pfg.stripe.egg-info/top_level.txt
wildcard/pfg/__init__.py
wildcard/pfg/stripe/__init__.py
wildcard/pfg/stripe/config.py
wildcard/pfg/stripe/configure.zcml
wildcard/pfg/stripe/field.py
wildcard/pfg/stripe/interfaces.py
wildcard/pfg/stripe/patches.py
wildcard/pfg/stripe/widget.py
wildcard/pfg/stripe/Extensions/Install.py
wildcard/pfg/stripe/Extensions/__init__.py
wildcard/pfg/stripe/profiles/default/factorytool.xml
wildcard/pfg/stripe/profiles/default/metadata.xml
wildcard/pfg/stripe/profiles/default/propertiestool.xml
wildcard/pfg/stripe/profiles/default/skins.xml
wildcard/pfg/stripe/profiles/default/types.xml
wildcard/pfg/stripe/profiles/default/workflows.xml
wildcard/pfg/stripe/profiles/default/types/FormFolder.xml
wildcard/pfg/stripe/profiles/default/types/FormStripeField.xml
wildcard/pfg/stripe/skins/pfgstripe/stripe.js
wildcard/pfg/stripe/skins/pfgstripe/stripewidget.pt
wildcard/pfg/stripe/tests/__init__.py
wildcard/pfg/stripe/tests/base.py
wildcard/pfg/stripe/tests/test_doctest.py