Metadata-Version: 1.1
Name: wildcard.pfg.stripe
Version: 1.1.0
Summary: Provides PFG stripe field
Home-page: https://github.com/collective/wildcard.pfg.stripe
Author: Nathan Van Gheem
Author-email: nathan@vangheem.us
License: GPL
Keywords: plone payment ecommerce stripe
Platform: UNKNOWN
Classifier: Framework :: Plone
Classifier: Intended Audience :: Developers
Classifier: License :: OSI Approved :: GNU General Public License (GPL)
